rtl/data_mem.v
module data_mem (
    input clk,
    input [31:0] addr,
    input [31:0] WriteData,
    input MemWrite, MemRead,

    output [31:0] ReadData
);

    // 32 words x 32 bits
    reg [31:0] memory [0:31];
    integer i;

    // Read
    assign ReadData = MemRead ? memory[addr[5:0] >> 2] : 32'b0; // or 32'bX??

    // Write
    always @(posedge clk) begin // No data reset
        if (MemWrite) begin
            memory[addr[5:0] >> 2] <= WriteData;
        end
    end

endmodule

rtl/alu.v
module alu (
    input [31:0] a, b,
    input [3:0] ALUCtrl,

    output reg [31:0] result,
    output zero
);

    always @(*) begin
        case (ALUCtrl)
            4'b0000: result = a & b; // AND
            4'b0001: result = a | b; // OR
            4'b0010: result = a + b; // ADD
            4'b0110: result = a - b; // SUB
            default: result = 32'd0;
        endcase
    end

    assign zero = (result == 0);

endmodule

rtl/sign_extend.v
module sign_extend (
    input [15:0] imm,
    output [31:0] extended_imm
);

    assign extended_imm = {{16{imm[15]}}, imm};

endmodule

rtl/reg_file.v
module reg_file (
    input clk, rst_n,
    input [4:0] ReadReg1, ReadReg2, WriteReg, // rs, rt, rd for R-Type respectively
    input RegWrite,
    input [31:0] WriteData, // word size = 32 bits

    output [31:0] ReadData1, ReadData2
);

    reg [31:0] registers [0:31]; // 32 registers of 32-bits

    // Combinational reads
    assign ReadData1 = (ReadReg1 == 0) ? 32'b0 : registers[ReadReg1]; // reg $0 stores constant value zero
    assign ReadData2 = (ReadReg2 == 0) ? 32'b0 : registers[ReadReg2];

    // Synchronous Write
    always @(posedge clk or negedge rst_n) begin
        if (!rst_n) begin
            for (i = 0; i < 32; i = i + 1)
                registers[i] <= 0; // initialize registers
        end else if (RegWrite && (WriteReg != 5'd0)) begin
            registers[WriteReg] <= WriteData;
        end
    end

endmodule

rtl/alu_control.v
module alu_control (
    input [1:0] ALUOp,
    input [5:0] funct,

    output reg [3:0] ALUCtrl
);

    // Funct (R_type)
    localparam add_r = 6'h20;
    localparam sub_r = 6'h22;
    localparam and_r = 6'h24;
    localparam or_r = 6'h25;

    always @(*) begin
        case (ALUOp)
            2'b10: case (funct)
                add_r: ALUCtrl = 4'b0010;
                sub_r: ALUCtrl = 4'b0110;
                and_r: ALUCtrl = 4'b0000;
                or_r:  ALUCtrl = 4'b0001;
            endcase
            2'b00: ALUCtrl = 4'b0010; // lw & sw
            2'b01: ALUCtrl = 4'b0110; // beq
            default: ALUCtrl = 4'd0;
        endcase
    end
endmodule

rtl/control.v
module control (
    input [5:0] opcode,
    
    output reg RegDst, Branch, MemRead, MemtoReg, MemWrite, ALUSrc, RegWrite,
    output reg [1:0] ALUOp
);

    // Opcode
    localparam RType = 6'h00;
    localparam lw = 6'h23;
    localparam sw = 6'h2B;
    localparam beq = 6'h04;


    always @(*) begin
        // initialize control signals to 0 (deactivated)
        ALUOp=2'b00;
		RegDst=1'b0;
        Branch=1'b0;
        MemRead=1'b0;
        MemtoReg=1'b0;
		MemWrite=1'b0;
		ALUSrc=1'b0;
        RegWrite=1'b0;
        
        case(opcode)
            RType: begin
                ALUOp = 2'b10;
                RegDst = 1'b1;
                RegWrite = 1'b1;
            end
            lw: begin
                ALUOp = 2'b00;
                MemRead = 1'b1;
                ALUSrc = 1'b1;
                MemtoReg = 1'b1;
                RegWrite = 1'b1;
            end
            sw: begin
                ALUOp = 2'b00;
                MemWrite = 1'b1;
                ALUSrc = 1'b1;
            end
            beq: begin
                ALUOp = 2'b01;
                Branch = 1'b1;
            end
        endcase	
    end

endmodule

rtl/inst_mem.v
module inst_mem (
    input [31:0] addr,
    output [31:0] inst
);

    reg [31:0] memory [0:31];

    initial begin 
		// Write instructions
    end

    assign inst = memory[addr >> 2];

endmodule

rtl/pc.v
module pc (
    input [31:0] next_addr,
    input clk, rst_n,
    output reg [31:0] addr
);

    always @(posedge clk or negedge rst_n) begin
        if (!rst_n)
            addr <= 32'b0;
        else
            addr <= next_addr;
    end

endmodule

rtl/mips_single_cycle.v
module mips_single_cycle (
    input clk, rst_n, // synchronize the reset signal?

    // Expose some of the key internal signals as primary outputs on the top-module
    // so Yosys doesn't optimize the CPU away
    output wire [31:0] pc_out, alu_out
);

    // =========================================
    // Program Counter
    // =========================================

    wire [31:0] addr;
    wire [31:0] next_addr;

    pc pc(
        .clk(clk), 
        .rst_n(rst_n),
        .next_addr(next_addr),
        .addr(addr)
    );


    // =========================================
    // Instruction Memory
    // =========================================

    wire [31:0] inst;

    inst_mem inst_mem(
        .addr(addr), .inst(inst)
    );


    // =========================================
    // Main Control
    // =========================================

    // R-format instruction
    wire [5:0] opcode = inst[31:26]; // 6 bits
    wire [4:0] rs = inst[25:21]; // 5 bits
    wire [4:0] rt = inst[20:16]; // 5 bits
    wire [4:0] rd = inst[15:11]; // 5 bits
    wire [5:0] funct = inst[5:0]; // 6 bits

    // I-format instruction
    wire [15:0] imm = inst[15:0]; // 16 bits

    // Control signals
    wire RegDst;
    wire ALUSrc;
    wire MemtoReg;
    wire RegWrite;
    wire MemRead;
    wire MemWrite;
    wire Branch;
    wire [1:0] ALUOp;

    control control(
        .opcode(opcode),
        .RegDst(RegDst),
        .Branch(Branch),
        .MemRead(MemRead),
        .MemtoReg(MemtoReg),
        .MemWrite(MemWrite),
        .ALUSrc(ALUSrc),
        .RegWrite(RegWrite),
        .ALUOp(ALUOp)
    );

    // =========================================
    // ALU Control
    // =========================================

    wire [3:0] ALUCtrl;

    alu_control alu_control(
        .ALUOp(ALUOp),
        .funct(funct),
        .ALUCtrl(ALUCtrl)
    );

    // =========================================
    // Register file
    // =========================================
    
    wire [31:0] ReadData1, ReadData2;
    wire [31:0] WriteData;

    wire [4:0] WriteReg;

    // MUX A: Choose destination register
    //        - R-type: rd
    //        - I-type: rt
    assign WriteReg = RegDst ? rd : rt;

    reg_file reg_file(
        .clk(clk),
        .rst_n(rst_n),
        .ReadReg1(rs),
        .ReadReg2(rt),
        .WriteReg(WriteReg),
        .RegWrite(RegWrite),
        .WriteData(WriteData),
        .ReadData1(ReadData1),
        .ReadData2(ReadData2)
    );


    // =========================================
    // Sign Extension
    // =========================================
    
    wire [31:0] extended_imm;

    sign_extend sign_extend(
        .imm(imm),
        .extended_imm(extended_imm)
    );

    // =========================================
    // ALU
    // =========================================

    wire [31:0] ALUsrc2;
    wire [31:0] ALUresult;
    wire zero;

    // MUX B: Choose ALU second input
    //        - R-type: ReadData2
    //        - beq: extended_imm
    assign ALUsrc2 = ALUSrc ? extended_imm : ReadData2;

    alu alu(
        .a(ReadData1),
        .b(ALUsrc2),
        .ALUCtrl(ALUCtrl),
        .result(ALUresult),
        .zero(zero)
    );

    // =========================================
    // Data Memory
    // =========================================

    wire [31:0] MemoryReadData;

    data_mem data_mem(
        .clk(clk),
        .addr(ALUresult),
        .WriteData(ReadData2),
        .MemWrite(MemWrite),
        .MemRead(MemRead),
        .ReadData(MemoryReadData)
    );

    // =========================================
    // WriteBack MUX
    // =========================================

    assign WriteData = MemtoReg ? MemoryReadData : ALUresult;

    // =========================================
    // Branch / Next PC
    // =========================================

    wire [31:0] branch_target;

    assign branch_target = addr + 32'd4 + (extended_imm << 2);
    assign next_addr = (Branch && zero) ? branch_target : addr + 32'd4; 


    // Connect internal wires to top-level output pins at the bottom:
    assign pc_out         = addr;
    assign alu_out        = ALUresult;

endmodule

tb/tb_mips_single_cycle.v
`timescale 1ns/1ps

module tb_mips_single_cycle;
    reg clk;
    reg rst_n;

    // DUT instantiation
    mips_single_cycle uut(
        .clk(clk),
        .rst_n(rst_n)
    );

    // Clock generation
    always #5 clk = ~clk;

    initial begin
        $dumpfile("waveform/tb_mips_single_cycle.vcd");
        $dumpvars(0, tb_mips_single_cycle);

        clk = 0;
        rst_n = 0;

        // ==========================================
        // Load program into instruction memory
        // ==========================================

        // Instruction 0
        uut.inst_mem.memory[0] = {6'h23, 5'd0, 5'd8, 16'd0}; // lw $t0, 0($zero)

        // Instruction 1
        uut.inst_mem.memory[1] = {6'h23, 5'd0, 5'd9, 16'd4}; // lw $t1, 4($zero)

        uut.inst_mem.memory[2] = {6'h00, 5'd8, 5'd9, 5'd10, 5'd0, 6'h20}; // add $t2, $t0, $t1
        uut.inst_mem.memory[3] = {6'h00, 5'd10, 5'd9, 5'd11, 5'd0, 6'h22}; // sub $t3, $t2, $t1
        uut.inst_mem.memory[4] = {6'h00, 5'd8, 5'd9, 5'd12, 5'd0, 6'h24}; // and $t4, $t0, $t1
        uut.inst_mem.memory[5] = {6'h00, 5'd8, 5'd9, 5'd13, 5'd0, 6'h25}; // or $t5, $t0, $t1

        uut.inst_mem.memory[6] = {6'h2B, 5'd0, 5'd10, 16'd8}; // sw $t2, 8($zero)
        uut.inst_mem.memory[7] = {6'h23, 5'd0, 5'd14, 16'd8}; // lw $t6, 8($zero)

        uut.inst_mem.memory[8] = {6'h04, 5'd10, 5'd14, 16'd1}; // beq $t2, $t6, 1
        uut.inst_mem.memory[9] = {6'h00, 5'd8, 5'd8, 5'd15, 5'd0, 6'h25}; // or $t7, $t0, $t0 - shouldn't execute
        uut.inst_mem.memory[10] = {6'h04, 5'd0, 5'd0, -16'sd1}; // beq $t2, $t6, -1


        // ==========================================
        // Initialize data memory
        // ==========================================

        uut.data_mem.memory[0] = 32'd10;
        uut.data_mem.memory[1] = 32'd6;


        // ==========================================
        // Reset
        // ==========================================

        #12;
        rst_n = 1;


        // ==========================================
        // Run CPU
        // ==========================================

        #100;

        // ==========================================
        // Inspect registers
        // ==========================================

        $display("Register 8  = %d, expected to be 10", uut.reg_file.registers[8]);
        $display("Register 9  = %d, expected to be 6", uut.reg_file.registers[9]);
        $display("Register 10  = %d, expected to be 16", uut.reg_file.registers[10]);
        $display("Register 11  = %d, expected to be 10", uut.reg_file.registers[11]);
        $display("Register 12  = %d, expected to be 2", uut.reg_file.registers[12]);
        $display("Register 13  = %d, expected to be 14", uut.reg_file.registers[13]);
        $display("Register 14  = %d, expected to be 16", uut.reg_file.registers[14]);
        $display("Register 15  = %d, expected to be 0", uut.reg_file.registers[15]);

        // ==========================================
        // Inspect memory
        // ==========================================

        $display("\nMemory[0] = %d", uut.data_mem.memory[0]);
        $display("Memory[1] = %d", uut.data_mem.memory[1]);
        $display("Memory[2] = %d", uut.data_mem.memory[2]);


        $finish;
    end
endmodule

waveform/tb_mips_single_cycle.vcd
$date
	Sat Sep  5 15:55:42 2026
$end
$version
	Icarus Verilog
$end
$timescale
	1ps
$end
$scope module tb_mips_single_cycle $end
$var reg 1 ! clk $end
$var reg 1 " rst_n $end
$scope module uut $end
$var wire 32 # alu_out [31:0] $end
$var wire 1 ! clk $end
$var wire 32 $ pc_out [31:0] $end
$var wire 1 " rst_n $end
$var wire 1 % zero $end
$var wire 5 & rt [4:0] $end
$var wire 5 ' rs [4:0] $end
$var wire 5 ( rd [4:0] $end
$var wire 6 ) opcode [5:0] $end
$var wire 32 * next_addr [31:0] $end
$var wire 32 + inst [31:0] $end
$var wire 16 , imm [15:0] $end
$var wire 6 - funct [5:0] $end
$var wire 32 . extended_imm [31:0] $end
$var wire 32 / branch_target [31:0] $end
$var wire 32 0 addr [31:0] $end
$var wire 5 1 WriteReg [4:0] $end
$var wire 32 2 WriteData [31:0] $end
$var wire 1 3 RegWrite $end
$var wire 1 4 RegDst $end
$var wire 32 5 ReadData2 [31:0] $end
$var wire 32 6 ReadData1 [31:0] $end
$var wire 1 7 MemtoReg $end
$var wire 32 8 MemoryReadData [31:0] $end
$var wire 1 9 MemWrite $end
$var wire 1 : MemRead $end
$var wire 1 ; Branch $end
$var wire 32 < ALUsrc2 [31:0] $end
$var wire 32 = ALUresult [31:0] $end
$var wire 1 > ALUSrc $end
$var wire 2 ? ALUOp [1:0] $end
$var wire 4 @ ALUCtrl [3:0] $end
$scope module alu $end
$var wire 32 A b [31:0] $end
$var wire 1 % zero $end
$var wire 32 B a [31:0] $end
$var wire 4 C ALUCtrl [3:0] $end
$var reg 32 D result [31:0] $end
$upscope $end
$scope module alu_control $end
$var wire 6 E funct [5:0] $end
$var wire 2 F ALUOp [1:0] $end
$var parameter 6 G add_r $end
$var parameter 6 H and_r $end
$var parameter 6 I or_r $end
$var parameter 6 J sub_r $end
$var reg 4 K ALUCtrl [3:0] $end
$upscope $end
$scope module control $end
$var wire 6 L opcode [5:0] $end
$var parameter 6 M RType $end
$var parameter 6 N beq $end
$var parameter 6 O lw $end
$var parameter 6 P sw $end
$var reg 2 Q ALUOp [1:0] $end
$var reg 1 > ALUSrc $end
$var reg 1 ; Branch $end
$var reg 1 : MemRead $end
$var reg 1 9 MemWrite $end
$var reg 1 7 MemtoReg $end
$var reg 1 4 RegDst $end
$var reg 1 3 RegWrite $end
$upscope $end
$scope module data_mem $end
$var wire 1 : MemRead $end
$var wire 1 9 MemWrite $end
$var wire 32 R addr [31:0] $end
$var wire 1 ! clk $end
$var wire 32 S WriteData [31:0] $end
$var wire 32 T ReadData [31:0] $end
$upscope $end
$scope module inst_mem $end
$var wire 32 U inst [31:0] $end
$var wire 32 V addr [31:0] $end
$upscope $end
$scope module pc $end
$var wire 1 ! clk $end
$var wire 32 W next_addr [31:0] $end
$var wire 1 " rst_n $end
$var reg 32 X addr [31:0] $end
$upscope $end
$scope module reg_file $end
$var wire 5 Y ReadReg1 [4:0] $end
$var wire 5 Z ReadReg2 [4:0] $end
$var wire 1 3 RegWrite $end
$var wire 32 [ WriteData [31:0] $end
$var wire 5 \ WriteReg [4:0] $end
$var wire 1 ! clk $end
$var wire 1 " rst_n $end
$var wire 32 ] ReadData2 [31:0] $end
$var wire 32 ^ ReadData1 [31:0] $end
$var integer 32 _ i [31:0] $end
$upscope $end
$scope module sign_extend $end
$var wire 16 ` imm [15:0] $end
$var wire 32 a extended_imm [31:0] $end
$upscope $end
$upscope $end
$upscope $end
$enddefinitions $end
$comment Show the parameter values. $end
$dumpall
b101011 P
b100011 O
b100 N
b0 M
b100010 J
b100101 I
b100100 H
b100000 G
$end
#0
$dumpvars
b0 a
b0 `
b100000 _
b0 ^
b0 ]
b1000 \
b1010 [
b1000 Z
b0 Y
b0 X
b100 W
b0 V
b10001100000010000000000000000000 U
b1010 T
b0 S
b0 R
b0 Q
b100011 L
b10 K
b0 F
b0 E
b0 D
b10 C
b0 B
b0 A
b10 @
b0 ?
1>
b0 =
b0 <
0;
1:
09
b1010 8
17
b0 6
b0 5
04
13
b1010 2
b1000 1
b0 0
b100 /
b0 .
b0 -
b0 ,
b10001100000010000000000000000000 +
b100 *
b100011 )
b0 (
b0 '
b1000 &
1%
b0 $
b0 #
0"
0!
$end
#5000
b100000 _
1!
#10000
0!
#12000
1"
#15000
b110 2
b110 [
b110 8
b110 T
0%
b100 #
b100 =
b100 D
b100 R
b100 <
b100 A
b100 .
b100 a
b1001 1
b1001 \
b100 ,
b100 `
b100 -
b100 E
b1001 &
b1001 Z
b10001100000010010000000000000100 +
b10001100000010010000000000000100 U
b1000 *
b1000 W
b0 5
b0 S
b0 ]
b11000 /
b100 $
b100 0
b100 V
b100 X
1!
#20000
0!
#25000
b10000 #
b10000 =
b10000 D
b10000 R
b1010 6
b1010 B
b1010 ^
b1010 1
b1010 \
b110 <
b110 A
b10000 2
b10000 [
b0 8
b0 T
b101000000100000 .
b101000000100000 a
14
b10 ?
b10 F
b10 Q
13
0>
07
0:
b101000000100000 ,
b101000000100000 `
b100000 -
b100000 E
b1010 (
b1000 '
b1000 Y
b0 )
b0 L
b1000010010101000000100000 +
b1000010010101000000100000 U
b110 5
b110 S
b110 ]
b1100 *
b1100 W
b10100000010001100 /
b1000 $
b1000 0
b1000 V
b1000 X
1!
#30000
0!
#35000
b1010 2
b1010 [
b1010 #
b1010 =
b1010 D
b1010 R
b10000 6
b10000 B
b10000 ^
b101100000100010 .
b101100000100010 a
b110 @
b110 C
b110 K
b1011 1
b1011 \
b101100000100010 ,
b101100000100010 `
b100010 -
b100010 E
b1011 (
b1010 '
b1010 Y
b1010010010101100000100010 +
b1010010010101100000100010 U
b10000 *
b10000 W
b10110000010011000 /
b1100 $
b1100 0
b1100 V
b1100 X
1!
#40000
0!
#45000
b10 2
b10 [
b10 #
b10 =
b10 D
b10 R
b1010 6
b1010 B
b1010 ^
b110000000100100 .
b110000000100100 a
b0 @
b0 C
b0 K
b1100 1
b1100 \
b110000000100100 ,
b110000000100100 `
b100100 -
b100100 E
b1100 (
b1000 '
b1000 Y
b1000010010110000000100100 +
b1000010010110000000100100 U
b10100 *
b10100 W
b11000000010100100 /
b10000 $
b10000 0
b10000 V
b10000 X
1!
#50000
0!
#55000
b1110 2
b1110 [
b1110 #
b1110 =
b1110 D
b1110 R
b110100000100101 .
b110100000100101 a
b1 @
b1 C
b1 K
b1101 1
b1101 \
b110100000100101 ,
b110100000100101 `
b100101 -
b100101 E
b1101 (
b1000010010110100000100101 +
b1000010010110100000100101 U
b11000 *
b11000 W
b11010000010101100 /
b10100 $
b10100 0
b10100 V
b10100 X
1!
#60000
0!
#65000
b1000 2
b1000 [
b1000 #
b1000 =
b1000 D
b1000 R
b10000 5
b10000 S
b10000 ]
b0 6
b0 B
b0 ^
b1000 <
b1000 A
b1000 .
b1000 a
b10 @
b10 C
b10 K
b1010 1
b1010 \
1>
19
03
04
b0 ?
b0 F
b0 Q
b1000 ,
b1000 `
b1000 -
b1000 E
b0 (
b1010 &
b1010 Z
b0 '
b0 Y
b101011 )
b101011 L
b10101100000010100000000000001000 +
b10101100000010100000000000001000 U
b11100 *
b11100 W
b111100 /
b11000 $
b11000 0
b11000 V
b11000 X
1!
#70000
0!
#75000
b0 5
b0 S
b0 ]
b10000 2
b10000 [
b10000 8
b10000 T
b1110 1
b1110 \
13
17
1:
1>
09
b1110 &
b1110 Z
b100011 )
b100011 L
b10001100000011100000000000001000 +
b10001100000011100000000000001000 U
b100000 *
b100000 W
b1000000 /
b11100 $
b11100 0
b11100 V
b11100 X
1!
#80000
0!
#85000
1%
b0 #
b0 =
b0 D
b0 R
b10000 6
b10000 B
b10000 ^
b10000 <
b10000 A
b0 2
b0 [
b0 8
b0 T
b1 .
b1 a
b110 @
b110 C
b110 K
1;
b1 ?
b1 F
b1 Q
03
0>
07
0:
b1 ,
b1 `
b1 -
b1 E
b1010 '
b1010 Y
b100 )
b100 L
b10001010011100000000000000001 +
b10001010011100000000000000001 U
b10000 5
b10000 S
b10000 ]
b101000 *
b101000 W
b101000 /
b100000 $
b100000 0
b100000 V
b100000 X
1!
#90000
0!
#95000
b0 2
b0 [
b0 <
b0 A
1%
b0 #
b0 =
b0 D
b0 R
b0 5
b0 S
b0 ]
b0 6
b0 B
b0 ^
b11111111111111111111111111111111 .
b11111111111111111111111111111111 a
b0 1
b0 \
b1111111111111111 ,
b1111111111111111 `
b111111 -
b111111 E
b11111 (
b0 &
b0 Z
b0 '
b0 Y
b10000000000001111111111111111 +
b10000000000001111111111111111 U
b101000 *
b101000 W
b101000 /
b101000 $
b101000 0
b101000 V
b101000 X
1!
