rtl/data_mem.v
module data_mem (
    input clk,
    input [31:0] addr,
    input [31:0] WriteData,
    input MemWrite, MemRead,

    output [31:0] ReadData
);

    // 32 words x 32 bits
    reg [31:0] memory [0:31];
    integer i;

    // Read
    assign ReadData = MemRead ? memory[addr[5:0] >> 2] : 32'b0; // or 32'bX??

    // Write
    always @(posedge clk) begin // No data reset
        if (MemWrite) begin
            memory[addr[5:0] >> 2] <= WriteData;
        end
    end

endmodule

rtl/alu.v
module alu (
    input [31:0] a, b,
    input [3:0] ALUCtrl,

    output reg [31:0] result,
    output zero
);

    always @(*) begin
        case (ALUCtrl)
            4'b0000: result = a & b; // AND
            4'b0001: result = a | b; // OR
            4'b0010: result = a + b; // ADD
            4'b0110: result = a - b; // SUB
            default: result = 32'd0;
        endcase
    end

    assign zero = (result == 0);

endmodule

rtl/sign_extend.v
module sign_extend (
    input [31:0] inst,
    output [31:0] extended_imm
);

    wire [15:0] imm = inst[15:0];
    assign extended_imm = {{16{imm[15]}}, imm};

endmodule

rtl/reg_file.v
module reg_file (
    input clk, rst_n,
    input [4:0] ReadReg1, ReadReg2, WriteReg, // rs, rt, rd for R-Type respectively
    input RegWrite,
    input [31:0] WriteData, // word size = 32 bits

    output [31:0] ReadData1, ReadData2
);

    reg [31:0] registers [0:31]; // 32 registers of 32-bits

    // Combinational reads
    assign ReadData1 = (ReadReg1 == 0) ? 32'b0 : registers[ReadReg1]; // reg $0 stores constant value zero
    assign ReadData2 = (ReadReg2 == 0) ? 32'b0 : registers[ReadReg2];

    // Synchronous Write
    always @(posedge clk or negedge rst_n) begin
        if (!rst_n) begin
            for (i = 0; i < 32; i = i + 1)
                registers[i] <= 0; // initialize registers
        end else if (RegWrite && (WriteReg != 5'd0)) begin
            registers[WriteReg] <= WriteData;
        end
    end

endmodule

rtl/alu_control.v
module alu_control (
    input [1:0] ALUOp,
    input [31:0] inst,

    output reg [3:0] ALUCtrl
);

    // Funct (R_type)
    wire [5:0] funct = inst[5:0];

    localparam add_r = 6'h20;
    localparam sub_r = 6'h22;
    localparam and_r = 6'h24;
    localparam or_r = 6'h25;

    always @(*) begin
        case (ALUOp)
            2'b10: case (funct)
                add_r: ALUCtrl = 4'b0010;
                sub_r: ALUCtrl = 4'b0110;
                and_r: ALUCtrl = 4'b0000;
                or_r:  ALUCtrl = 4'b0001;
            endcase
            2'b00: ALUCtrl = 4'b0010; // lw & sw
            2'b01: ALUCtrl = 4'b0110; // beq
            defualt: ALUCtrl = 4'd0;
        endcase
    end
endmodule

rtl/control.v
module control (
    input [31:0] inst,
    
    output reg RegDst, Branch, MemRead, MemtoReg, MemWrite, ALUSrc, RegWrite,
    output reg [1:0] ALUOp
);

    // Opcode
    wire [5:0] opcode = inst[31:26];

    localparam RType = 6'h00;
    localparam lw = 6'h23;
    localparam sw = 6'h2B;
    localparam beq = 6'h04;


    always @(*) begin
        // initialize control signals to 0 (deactivated)
        ALUOp=2'b00;
		RegDst=1'b0;
        Branch=1'b0;
        MemRead=1'b0;
        MemtoReg=1'b0;
		MemWrite=1'b0;
		ALUSrc=1'b0;
        RegWrite=1'b0;

        if (inst != 0) begin
            case(opcode)
                RType: begin
                    ALUOp = 2'b10;
                    RegDst = 1'b1;
                    RegWrite = 1'b1;
                end
                lw: begin
                    ALUOp = 2'b00;
                    MemRead = 1'b1;
                    ALUSrc = 1'b1;
                    MemtoReg = 1'b1;
                    RegWrite = 1'b1;
                end
                sw: begin
                    ALUOp = 2'b00;
                    MemWrite = 1'b1;
                    ALUSrc = 1'b1;
                end
                beq: begin
                    ALUOp = 2'b01;
                    Branch = 1'b1;
                end
            endcase
        end
		
    end
    


endmodule

rtl/inst_mem.v
module inst_mem (
    input [31:0] addr,
    output [31:0] inst
);

    reg [31:0] memory [0:31];

    initial begin 
		// Write instructions
    end

    assign inst = memory[addr >> 2];

endmodule

rtl/pc.v
module pc (
    input [31:0] next_addr,
    input clk, rst_n,
    output reg [31:0] addr
);

    always @(posedge clk or negedge rst_n) begin
        if (!rst_n)
            addr <= 32'b0;
        else
            addr <= next_addr;
    end

endmodule

rtl/mips_single_cycle.v
module mips_single_cycle (
    input clk, rst_n // synchronize the reset signal?
);

    // =========================================
    // Program Counter
    // =========================================

    wire [31:0] addr;
    wire [31:0] next_addr;

    pc pc(
        .clk(clk), 
        .rst_n(rst_n),
        .next_addr(next_addr),
        .addr(addr)
    );


    // =========================================
    // Instruction Memory
    // =========================================

    wire [31:0] inst;

    inst_mem inst_mem(
        .addr(addr), .inst(inst)
    );


    // =========================================
    // Main Control
    // =========================================

    // R-format instruction
    wire [5:0] opcode = inst[31:26]; // 6 bits
    wire [4:0] rs = inst[25:21]; // 5 bits
    wire [4:0] rt = inst[20:16]; // 5 bits
    wire [4:0] rd = inst[15:11]; // 5 bits
    wire [5:0] funct = inst[5:0]; // 6 bits

    // I-format instruction
    wire [15:0] imm = inst[15:0]; // 16 bits

    // Control signals
    wire RegDst;
    wire ALUSrc;
    wire MemtoReg;
    wire RegWrite;
    wire MemRead;
    wire MemWrite;
    wire Branch;
    wire [1:0] ALUOp;

    control control(
        .inst(inst),
        .RegDst(RegDst),
        .Branch(Branch),
        .MemRead(MemRead),
        .MemtoReg(MemtoReg),
        .MemWrite(MemWrite),
        .ALUSrc(ALUSrc),
        .RegWrite(RegWrite),
        .ALUOp(ALUOp)
    );

    // =========================================
    // ALU Control
    // =========================================

    wire [3:0] ALUCtrl;

    alu_control alu_control(
        .ALUOp(ALUOp),
        .inst(inst),
        .ALUCtrl(ALUCtrl)
    );

    // =========================================
    // Register file
    // =========================================
    
    wire [31:0] ReadData1, ReadData2;
    wire [31:0] WriteData;

    wire [4:0] WriteReg;

    // MUX A: Choose destination register
    //        - R-type: rd
    //        - I-type: rt
    assign WriteReg = RegDst ? rd : rt;

    reg_file reg_file(
        .clk(clk),
        .rst_n(rst_n),
        .ReadReg1(inst[25:21]),
        .ReadReg2(inst[20:16]),
        .WriteReg(WriteReg),
        .RegWrite(RegWrite),
        .WriteData(WriteData),
        .ReadData1(ReadData1),
        .ReadData2(ReadData2)
    );


    // =========================================
    // Sign Extension
    // =========================================
    
    wire [31:0] extended_imm;

    sign_extend sign_extend(
        .inst(inst),
        .extended_imm(extended_imm)
    );

    // =========================================
    // ALU
    // =========================================

    wire [31:0] ALUsrc2;
    wire [31:0] ALUresult;
    wire zero;

    // MUX B: Choose ALU second input
    //        - R-type: ReadData2
    //        - beq: extended_imm
    assign ALUsrc2 = ALUSrc ? extended_imm : ReadData2;

    alu alu(
        .a(ReadData1),
        .b(ALUsrc2),
        .ALUCtrl(ALUCtrl),
        .result(ALUresult),
        .zero(zero)
    );

    // =========================================
    // Data Memory
    // =========================================

    wire [31:0] MemoryReadData;

    data_mem data_mem(
        .clk(clk),
        .addr(ALUresult),
        .WriteData(ReadData2),
        .MemWrite(MemWrite),
        .MemRead(MemRead),
        .ReadData(MemoryReadData)
    );

    // =========================================
    // WriteBack MUX
    // =========================================

    assign WriteData = MemtoReg ? MemoryReadData : ALUresult;

    // =========================================
    // Branch / Next PC
    // =========================================

    wire [31:0] branch_target;

    assign branch_target = addr + 32'd4 + (extended_imm << 2);
    assign next_addr = (Branch && zero) ? branch_target : addr + 32'd4; 

endmodule

tb/tb_mips_single_cycle.v
`timescale 1ns/1ps

module tb_mips_single_cycle;
    reg clk;
    reg rst_n;

    // DUT instantiation
    mips_single_cycle uut(
        .clk(clk),
        .rst_n(rst_n)
    );

    // Clock generation
    always #5 clk = ~clk;

    initial begin
        $dumpfile("waveform/tb_mips_single_cycle.vcd");
        $dumpvars(0, tb_mips_single_cycle);

        clk = 0;
        rst_n = 0;

        // ==========================================
        // Load program into instruction memory
        // ==========================================

        // Instruction 0
        uut.inst_mem.memory[0] = {6'h23, 5'd0, 5'd8, 16'd0}; // lw $t0, 0($zero)

        // Instruction 1
        uut.inst_mem.memory[1] = {6'h23, 5'd0, 5'd9, 16'd4}; // lw $t1, 4($zero)

        uut.inst_mem.memory[2] = {6'h00, 5'd8, 5'd9, 5'd10, 5'd0, 6'h20}; // add $t2, $t0, $t1
        uut.inst_mem.memory[3] = {6'h00, 5'd10, 5'd9, 5'd11, 5'd0, 6'h22}; // sub $t3, $t2, $t1
        uut.inst_mem.memory[4] = {6'h00, 5'd8, 5'd9, 5'd12, 5'd0, 6'h24}; // and $t4, $t0, $t1
        uut.inst_mem.memory[5] = {6'h00, 5'd8, 5'd9, 5'd13, 5'd0, 6'h25}; // or $t5, $t0, $t1

        uut.inst_mem.memory[6] = {6'h2B, 5'd0, 5'd10, 16'd8}; // sw $t2, 8($zero)
        uut.inst_mem.memory[7] = {6'h23, 5'd0, 5'd14, 16'd8}; // lw $t6, 8($zero)

        uut.inst_mem.memory[8] = {6'h04, 5'd10, 5'd14, 16'd1}; // beq $t2, $t6, 1
        uut.inst_mem.memory[9] = {6'h00, 5'd8, 5'd8, 5'd15, 5'd0, 6'h25}; // or $t7, $t0, $t0 - shouldn't execute
        uut.inst_mem.memory[10] = {6'h04, 5'd0, 5'd0, -16'sd1}; // beq $t2, $t6, -1


        // ==========================================
        // Initialize data memory
        // ==========================================

        uut.data_mem.memory[0] = 32'd10;
        uut.data_mem.memory[1] = 32'd6;


        // ==========================================
        // Reset
        // ==========================================

        #12;
        rst_n = 1;


        // ==========================================
        // Run CPU
        // ==========================================

        #100;

        // ==========================================
        // Inspect registers
        // ==========================================

        $display("Register 8  = %d, expected to be 10", uut.reg_file.registers[8]);
        $display("Register 9  = %d, expected to be 6", uut.reg_file.registers[9]);
        $display("Register 10  = %d, expected to be 16", uut.reg_file.registers[10]);
        $display("Register 11  = %d, expected to be 10", uut.reg_file.registers[11]);
        $display("Register 12  = %d, expected to be 2", uut.reg_file.registers[12]);
        $display("Register 13  = %d, expected to be 14", uut.reg_file.registers[13]);
        $display("Register 14  = %d, expected to be 16", uut.reg_file.registers[14]);
        $display("Register 15  = %d, expected to be 0", uut.reg_file.registers[15]);

        // ==========================================
        // Inspect memory
        // ==========================================

        $display("\nMemory[0] = %d", uut.data_mem.memory[0]);
        $display("Memory[1] = %d", uut.data_mem.memory[1]);
        $display("Memory[2] = %d", uut.data_mem.memory[2]);


        $finish;
    end
endmodule

waveform/tb_mips_single_cycle.vcd
$date
	Sat Sep  5 12:12:03 2026
$end
$version
	Icarus Verilog
$end
$timescale
	1ps
$end
$scope module tb_mips_single_cycle $end
$var reg 1 ! clk $end
$var reg 1 " rst_n $end
$scope module uut $end
$var wire 1 ! clk $end
$var wire 1 " rst_n $end
$var wire 1 # zero $end
$var wire 5 $ rt [4:0] $end
$var wire 5 % rs [4:0] $end
$var wire 5 & rd [4:0] $end
$var wire 6 ' opcode [5:0] $end
$var wire 32 ( next_addr [31:0] $end
$var wire 32 ) inst [31:0] $end
$var wire 16 * imm [15:0] $end
$var wire 6 + funct [5:0] $end
$var wire 32 , extended_imm [31:0] $end
$var wire 32 - branch_target [31:0] $end
$var wire 32 . addr [31:0] $end
$var wire 5 / WriteReg [4:0] $end
$var wire 32 0 WriteData [31:0] $end
$var wire 1 1 RegWrite $end
$var wire 1 2 RegDst $end
$var wire 32 3 ReadData2 [31:0] $end
$var wire 32 4 ReadData1 [31:0] $end
$var wire 1 5 MemtoReg $end
$var wire 32 6 MemoryReadData [31:0] $end
$var wire 1 7 MemWrite $end
$var wire 1 8 MemRead $end
$var wire 1 9 Branch $end
$var wire 32 : ALUsrc2 [31:0] $end
$var wire 32 ; ALUresult [31:0] $end
$var wire 1 < ALUSrc $end
$var wire 2 = ALUOp [1:0] $end
$var wire 4 > ALUCtrl [3:0] $end
$scope module alu $end
$var wire 32 ? b [31:0] $end
$var wire 1 # zero $end
$var wire 32 @ a [31:0] $end
$var wire 4 A ALUCtrl [3:0] $end
$var reg 32 B result [31:0] $end
$upscope $end
$scope module alu_control $end
$var wire 32 C inst [31:0] $end
$var wire 6 D funct [5:0] $end
$var wire 2 E ALUOp [1:0] $end
$var parameter 6 F add_r $end
$var parameter 6 G and_r $end
$var parameter 6 H or_r $end
$var parameter 6 I sub_r $end
$var reg 4 J ALUCtrl [3:0] $end
$upscope $end
$scope module control $end
$var wire 6 K opcode [5:0] $end
$var wire 32 L inst [31:0] $end
$var parameter 6 M RType $end
$var parameter 6 N beq $end
$var parameter 6 O lw $end
$var parameter 6 P sw $end
$var reg 2 Q ALUOp [1:0] $end
$var reg 1 < ALUSrc $end
$var reg 1 9 Branch $end
$var reg 1 8 MemRead $end
$var reg 1 7 MemWrite $end
$var reg 1 5 MemtoReg $end
$var reg 1 2 RegDst $end
$var reg 1 1 RegWrite $end
$upscope $end
$scope module data_mem $end
$var wire 1 8 MemRead $end
$var wire 1 7 MemWrite $end
$var wire 32 R addr [31:0] $end
$var wire 1 ! clk $end
$var wire 32 S WriteData [31:0] $end
$var wire 32 T ReadData [31:0] $end
$upscope $end
$scope module inst_mem $end
$var wire 32 U inst [31:0] $end
$var wire 32 V addr [31:0] $end
$upscope $end
$scope module pc $end
$var wire 1 ! clk $end
$var wire 32 W next_addr [31:0] $end
$var wire 1 " rst_n $end
$var reg 32 X addr [31:0] $end
$upscope $end
$scope module reg_file $end
$var wire 5 Y ReadReg1 [4:0] $end
$var wire 5 Z ReadReg2 [4:0] $end
$var wire 1 1 RegWrite $end
$var wire 32 [ WriteData [31:0] $end
$var wire 5 \ WriteReg [4:0] $end
$var wire 1 ! clk $end
$var wire 1 " rst_n $end
$var wire 32 ] ReadData2 [31:0] $end
$var wire 32 ^ ReadData1 [31:0] $end
$var integer 32 _ i [31:0] $end
$upscope $end
$scope module sign_extend $end
$var wire 32 ` inst [31:0] $end
$var wire 16 a imm [15:0] $end
$var wire 32 b extended_imm [31:0] $end
$upscope $end
$upscope $end
$upscope $end
$enddefinitions $end
$comment Show the parameter values. $end
$dumpall
b101011 P
b100011 O
b100 N
b0 M
b100010 I
b100101 H
b100100 G
b100000 F
$end
#0
$dumpvars
b0 b
b0 a
b10001100000010000000000000000000 `
b100000 _
b0 ^
b0 ]
b1000 \
b1010 [
b1000 Z
b0 Y
b0 X
b100 W
b0 V
b10001100000010000000000000000000 U
b1010 T
b0 S
b0 R
b0 Q
b10001100000010000000000000000000 L
b100011 K
b10 J
b0 E
b0 D
b10001100000010000000000000000000 C
b0 B
b10 A
b0 @
b0 ?
b10 >
b0 =
1<
b0 ;
b0 :
09
18
07
b1010 6
15
b0 4
b0 3
02
11
b1010 0
b1000 /
b0 .
b100 -
b0 ,
b0 +
b0 *
b10001100000010000000000000000000 )
b100 (
b100011 '
b0 &
b0 %
b1000 $
1#
0"
0!
$end
#5000
b100000 _
1!
#10000
0!
#12000
1"
#15000
b110 0
b110 [
b110 6
b110 T
0#
b100 ;
b100 B
b100 R
b100 :
b100 ?
b100 ,
b100 b
b1001 /
b1001 \
b100 a
b100 D
b1001 Z
b100 *
b100 +
b1001 $
11
1<
15
18
b10001100000010010000000000000100 )
b10001100000010010000000000000100 C
b10001100000010010000000000000100 L
b10001100000010010000000000000100 U
b10001100000010010000000000000100 `
b1000 (
b1000 W
b0 3
b0 S
b0 ]
b11000 -
b100 .
b100 V
b100 X
1!
#20000
0!
#25000
b10000 ;
b10000 B
b10000 R
b1010 /
b1010 \
b110 :
b110 ?
b10000 0
b10000 [
b0 6
b0 T
b1010 4
b1010 @
b1010 ^
b101000000100000 ,
b101000000100000 b
12
b10 =
b10 E
b10 Q
b101000000100000 a
b0 K
b100000 D
b1000 Y
b101000000100000 *
b100000 +
b1010 &
b1000 %
b0 '
11
0<
05
08
b1000010010101000000100000 )
b1000010010101000000100000 C
b1000010010101000000100000 L
b1000010010101000000100000 U
b1000010010101000000100000 `
b110 3
b110 S
b110 ]
b1100 (
b1100 W
b10100000010001100 -
b1000 .
b1000 V
b1000 X
1!
#30000
0!
#35000
b1010 0
b1010 [
b10000 4
b10000 @
b10000 ^
b1010 ;
b1010 B
b1010 R
b101100000100010 ,
b101100000100010 b
b1011 /
b1011 \
b110 >
b110 A
b110 J
b101100000100010 a
b100010 D
b1010 Y
b101100000100010 *
b100010 +
b1011 &
b1010 %
11
12
b10 =
b10 E
b10 Q
b1010010010101100000100010 )
b1010010010101100000100010 C
b1010010010101100000100010 L
b1010010010101100000100010 U
b1010010010101100000100010 `
b10000 (
b10000 W
b10110000010011000 -
b1100 .
b1100 V
b1100 X
1!
#40000
0!
#45000
b10 0
b10 [
b1010 4
b1010 @
b1010 ^
0#
b10 ;
b10 B
b10 R
b110000000100100 ,
b110000000100100 b
b1100 /
b1100 \
b0 >
b0 A
b0 J
b110000000100100 a
b100100 D
b1000 Y
b110000000100100 *
b100100 +
b1100 &
b1000 %
11
12
b10 =
b10 E
b10 Q
b1000010010110000000100100 )
b1000010010110000000100100 C
b1000010010110000000100100 L
b1000010010110000000100100 U
b1000010010110000000100100 `
b10100 (
b10100 W
b11000000010100100 -
b10000 .
b10000 V
b10000 X
1!
#50000
0!
#55000
b1110 0
b1110 [
b1110 ;
b1110 B
b1110 R
b110100000100101 ,
b110100000100101 b
b1101 /
b1101 \
b1 >
b1 A
b1 J
b110100000100101 a
b100101 D
b110100000100101 *
b100101 +
b1101 &
11
12
b10 =
b10 E
b10 Q
b1000010010110100000100101 )
b1000010010110100000100101 C
b1000010010110100000100101 L
b1000010010110100000100101 U
b1000010010110100000100101 `
b11000 (
b11000 W
b11010000010101100 -
b10100 .
b10100 V
b10100 X
1!
#60000
0!
#65000
b1000 0
b1000 [
b1000 ;
b1000 B
b1000 R
b1000 :
b1000 ?
b10 >
b10 A
b10 J
b10000 3
b10000 S
b10000 ]
b0 4
b0 @
b0 ^
b1000 ,
b1000 b
1<
17
b1010 /
b1010 \
b1000 a
b101011 K
b1000 D
b1010 Z
b0 Y
b1000 *
b1000 +
b0 &
b1010 $
b0 %
b101011 '
01
02
b0 =
b0 E
b0 Q
b10101100000010100000000000001000 )
b10101100000010100000000000001000 C
b10101100000010100000000000001000 L
b10101100000010100000000000001000 U
b10101100000010100000000000001000 `
b11100 (
b11100 W
b111100 -
b11000 .
b11000 V
b11000 X
1!
#70000
0!
#75000
b10000 0
b10000 [
b10000 6
b10000 T
b0 3
b0 S
b0 ]
11
15
18
b1110 /
b1110 \
b100011 K
b1110 Z
b1110 $
b100011 '
1<
07
b10001100000011100000000000001000 )
b10001100000011100000000000001000 C
b10001100000011100000000000001000 L
b10001100000011100000000000001000 U
b10001100000011100000000000001000 `
b100000 (
b100000 W
b1000000 -
b11100 .
b11100 V
b11100 X
1!
#80000
0!
#85000
1#
b0 ;
b0 B
b0 R
b110 >
b110 A
b110 J
b10000 :
b10000 ?
b0 0
b0 [
b0 6
b0 T
b10000 4
b10000 @
b10000 ^
b1 ,
b1 b
19
b1 =
b1 E
b1 Q
b1 a
b100 K
b1 D
b1010 Y
b1 *
b1 +
b1010 %
b100 '
01
0<
05
08
b10001010011100000000000000001 )
b10001010011100000000000000001 C
b10001010011100000000000000001 L
b10001010011100000000000000001 U
b10001010011100000000000000001 `
b10000 3
b10000 S
b10000 ]
b101000 (
b101000 W
b101000 -
b100000 .
b100000 V
b100000 X
1!
#90000
0!
#95000
b0 0
b0 [
b0 :
b0 ?
1#
b0 ;
b0 B
b0 R
b0 3
b0 S
b0 ]
b0 4
b0 @
b0 ^
b11111111111111111111111111111111 ,
b11111111111111111111111111111111 b
b0 /
b0 \
b1111111111111111 a
b111111 D
b0 Z
b0 Y
b1111111111111111 *
b111111 +
b11111 &
b0 $
b0 %
19
b1 =
b1 E
b1 Q
b10000000000001111111111111111 )
b10000000000001111111111111111 C
b10000000000001111111111111111 L
b10000000000001111111111111111 U
b10000000000001111111111111111 `
b101000 (
b101000 W
b101000 -
b101000 .
b101000 V
b101000 X
1!
